<?xml version="1.0" encoding="UTF-8"?>
<objects serializationModel="Studio.01.10.00">
    <object class="AudioFile" id="{f1ef5ed6-5e6c-4a40-9d06-0dd1271c669e}">
        <property name="assetPath">
            <value>stepsMontain_14.wav</value>
        </property>
        <property name="frequencyInKHz">
            <value>44.0999985</value>
        </property>
        <property name="channelCount">
            <value>2</value>
        </property>
        <property name="length">
            <value>0.3831292517006803</value>
        </property>
        <relationship name="masterAssetFolder">
            <destination>{e3ac76b4-0cdc-45d3-8225-de35519576fa}</destination>
        </relationship>
    </object>
</objects>
